{
  "nodes": [
    {
      "data": {
        "id": "EM_JASS",
        "label": "JASS",
        "type": "emiten"
      }
    },
    {
      "data": {
        "id": "SH_SATS_LTD_",
        "label": "SATS LTD.",
        "type": "shareholder"
      }
    },
    {
      "data": {
        "id": "KP_TEMASEK_HOLDINGS",
        "label": "Temasek Holdings",
        "type": "keyperson"
      }
    }
  ],
  "edges": [
    {
      "data": {
        "id": "EM_JASS_SH_SATS_LTD_",
        "source": "EM_JASS",
        "target": "SH_SATS_LTD_",
        "relation": "HAS_SHAREHOLDER"
      }
    },
    {
      "data": {
        "id": "EM_JASS_KP_TEMASEK_HOLDINGS",
        "source": "EM_JASS",
        "target": "KP_TEMASEK_HOLDINGS",
        "relation": "HAS_KEYPERSON"
      }
    }
  ]
}