{
  "nodes": [
    {
      "data": {
        "id": "EM_NIPS",
        "label": "NIPS",
        "type": "emiten"
      }
    },
    {
      "data": {
        "id": "SH_PT_TRINITAN_INTERNATIONAL",
        "label": "PT TRINITAN INTERNATIONAL",
        "type": "shareholder"
      }
    },
    {
      "data": {
        "id": "KP_KELUARGA_TANDIONO",
        "label": "Keluarga Tandiono",
        "type": "keyperson"
      }
    },
    {
      "data": {
        "id": "SH_TRITAN_ADHITAMA_NUGRAHA",
        "label": "TRITAN ADHITAMA NUGRAHA",
        "type": "shareholder"
      }
    },
    {
      "data": {
        "id": "SH_FERRY_J_ROBERTUS_TANDIONO",
        "label": "FERRY J. ROBERTUS TANDIONO",
        "type": "shareholder"
      }
    },
    {
      "data": {
        "id": "KP_FERRY_TANDIONO",
        "label": "Ferry Tandiono",
        "type": "keyperson"
      }
    },
    {
      "data": {
        "id": "SH_PT_INDOLIFE_PENSIONTAMA",
        "label": "PT. INDOLIFE PENSIONTAMA",
        "type": "shareholder"
      }
    },
    {
      "data": {
        "id": "KP_SALIM_GROUP",
        "label": "Salim Group",
        "type": "keyperson"
      }
    },
    {
      "data": {
        "id": "SH_TRIMEGAH_SEKURITAS_INDONESIA",
        "label": "TRIMEGAH SEKURITAS INDONESIA",
        "type": "shareholder"
      }
    },
    {
      "data": {
        "id": "KP_GARIBALDI_THOHIR",
        "label": "Garibaldi Thohir",
        "type": "keyperson"
      }
    }
  ],
  "edges": [
    {
      "data": {
        "id": "EM_NIPS_SH_PT_TRINITAN_INTERNATIONAL",
        "source": "EM_NIPS",
        "target": "SH_PT_TRINITAN_INTERNATIONAL",
        "relation": "HAS_SHAREHOLDER"
      }
    },
    {
      "data": {
        "id": "EM_NIPS_KP_KELUARGA_TANDIONO",
        "source": "EM_NIPS",
        "target": "KP_KELUARGA_TANDIONO",
        "relation": "HAS_KEYPERSON"
      }
    },
    {
      "data": {
        "id": "EM_NIPS_SH_TRITAN_ADHITAMA_NUGRAHA",
        "source": "EM_NIPS",
        "target": "SH_TRITAN_ADHITAMA_NUGRAHA",
        "relation": "HAS_SHAREHOLDER"
      }
    },
    {
      "data": {
        "id": "EM_NIPS_KP_KELUARGA_TANDIONO",
        "source": "EM_NIPS",
        "target": "KP_KELUARGA_TANDIONO",
        "relation": "HAS_KEYPERSON"
      }
    },
    {
      "data": {
        "id": "EM_NIPS_SH_FERRY_J_ROBERTUS_TANDIONO",
        "source": "EM_NIPS",
        "target": "SH_FERRY_J_ROBERTUS_TANDIONO",
        "relation": "HAS_SHAREHOLDER"
      }
    },
    {
      "data": {
        "id": "EM_NIPS_KP_FERRY_TANDIONO",
        "source": "EM_NIPS",
        "target": "KP_FERRY_TANDIONO",
        "relation": "HAS_KEYPERSON"
      }
    },
    {
      "data": {
        "id": "EM_NIPS_SH_PT_INDOLIFE_PENSIONTAMA",
        "source": "EM_NIPS",
        "target": "SH_PT_INDOLIFE_PENSIONTAMA",
        "relation": "HAS_SHAREHOLDER"
      }
    },
    {
      "data": {
        "id": "EM_NIPS_KP_SALIM_GROUP",
        "source": "EM_NIPS",
        "target": "KP_SALIM_GROUP",
        "relation": "HAS_KEYPERSON"
      }
    },
    {
      "data": {
        "id": "EM_NIPS_SH_TRIMEGAH_SEKURITAS_INDONESIA",
        "source": "EM_NIPS",
        "target": "SH_TRIMEGAH_SEKURITAS_INDONESIA",
        "relation": "HAS_SHAREHOLDER"
      }
    },
    {
      "data": {
        "id": "EM_NIPS_KP_GARIBALDI_THOHIR",
        "source": "EM_NIPS",
        "target": "KP_GARIBALDI_THOHIR",
        "relation": "HAS_KEYPERSON"
      }
    }
  ]
}