{
  "nodes": [
    {
      "data": {
        "id": "EM_SOSS",
        "label": "SOSS",
        "type": "emiten"
      }
    },
    {
      "data": {
        "id": "SH_PURAGRAHA_DIAN_PERTIWI",
        "label": "PURAGRAHA DIAN PERTIWI",
        "type": "shareholder"
      }
    },
    {
      "data": {
        "id": "KP_PERUSAHAAN_PERLU_CEK_AHU_",
        "label": "Perusahaan (Perlu Cek AHU)",
        "type": "keyperson"
      }
    },
    {
      "data": {
        "id": "SH_ALSOK_BASS_INDONESIA",
        "label": "ALSOK BASS INDONESIA",
        "type": "shareholder"
      }
    },
    {
      "data": {
        "id": "KP_ALSOK_JEPANG_",
        "label": "Alsok (Jepang)",
        "type": "keyperson"
      }
    }
  ],
  "edges": [
    {
      "data": {
        "id": "EM_SOSS_SH_PURAGRAHA_DIAN_PERTIWI",
        "source": "EM_SOSS",
        "target": "SH_PURAGRAHA_DIAN_PERTIWI",
        "relation": "HAS_SHAREHOLDER"
      }
    },
    {
      "data": {
        "id": "EM_SOSS_KP_PERUSAHAAN_PERLU_CEK_AHU_",
        "source": "EM_SOSS",
        "target": "KP_PERUSAHAAN_PERLU_CEK_AHU_",
        "relation": "HAS_KEYPERSON"
      }
    },
    {
      "data": {
        "id": "EM_SOSS_SH_ALSOK_BASS_INDONESIA",
        "source": "EM_SOSS",
        "target": "SH_ALSOK_BASS_INDONESIA",
        "relation": "HAS_SHAREHOLDER"
      }
    },
    {
      "data": {
        "id": "EM_SOSS_KP_ALSOK_JEPANG_",
        "source": "EM_SOSS",
        "target": "KP_ALSOK_JEPANG_",
        "relation": "HAS_KEYPERSON"
      }
    }
  ]
}