{
  "nodes": [
    {
      "data": {
        "id": "EM_MBAP",
        "label": "MBAP",
        "type": "emiten"
      }
    },
    {
      "data": {
        "id": "SH_WAHANA_SENTOSA_CEMERLANG",
        "label": "WAHANA SENTOSA CEMERLANG",
        "type": "shareholder"
      }
    },
    {
      "data": {
        "id": "KP_KELUARGA_WIDJAJA",
        "label": "Keluarga Widjaja",
        "type": "keyperson"
      }
    },
    {
      "data": {
        "id": "SH_WAHANA_BATUBARA_INDONESIA",
        "label": "WAHANA BATUBARA INDONESIA",
        "type": "shareholder"
      }
    }
  ],
  "edges": [
    {
      "data": {
        "id": "EM_MBAP_SH_WAHANA_SENTOSA_CEMERLANG",
        "source": "EM_MBAP",
        "target": "SH_WAHANA_SENTOSA_CEMERLANG",
        "relation": "HAS_SHAREHOLDER"
      }
    },
    {
      "data": {
        "id": "EM_MBAP_KP_KELUARGA_WIDJAJA",
        "source": "EM_MBAP",
        "target": "KP_KELUARGA_WIDJAJA",
        "relation": "HAS_KEYPERSON"
      }
    },
    {
      "data": {
        "id": "EM_MBAP_SH_WAHANA_BATUBARA_INDONESIA",
        "source": "EM_MBAP",
        "target": "SH_WAHANA_BATUBARA_INDONESIA",
        "relation": "HAS_SHAREHOLDER"
      }
    },
    {
      "data": {
        "id": "EM_MBAP_KP_KELUARGA_WIDJAJA",
        "source": "EM_MBAP",
        "target": "KP_KELUARGA_WIDJAJA",
        "relation": "HAS_KEYPERSON"
      }
    }
  ]
}